{
    "timeStamp": "1512489454",
    "devID": "0000000001040921",
    "totalScanTime": 63,
    "wakeCounter": 1258,
    "ble": {
        "scan1": {
            "00:A0:50:B2:96:DF": "-81",
            "00:A0:50:C5:76:91": "-71",
            "00:A0:50:C5:75:B5": "-76",
            "00:A0:50:B2:96:B2": "-70"
        }
    },
    "dht": [
        " 30,47,1512489460"
    ],
    "gsm": {
        "scan1": [
            "AT+CREG? +CREG: 0,1  OK",
            "AT+CENG=3 OK",
            "AT+COPS=? +COPS: (2,\"IDEA Cellular Limited\",\"IDEA\",\"40422\"),(3,\"405804\",\"405804\",\"405804\"),(3,\"BPL USWEST (Maharastra)\",\"BPL MO\",\"40427\"),(3,\"405037\",\"405037\",\"405037\"),(3,\"Maharashtra\",\"CellOne\",\"40466\"),(3,\"AirTel\",\"AirTel\",\"40490\"),,(0-4),(0-2)  OK",
            "AT+CSQ +CSQ: 16,0  OK",
            "AT+CENG? +CENG: 3,0  +CENG: 0,\"404,22,278d,206d,25,32\" +CENG: 1,\"404,22,278d,3112,08,14\" +CENG: 2,\"404,22,278d,2654,02,10\" +CENG: 3,\"404,22,278d,1506,46,10\" +CENG: 4,\"404,22,278d,1507,04,09\" +CENG: 5,\"404,22,278d,1505,29,09\" +CENG: 6,\",,0000,ffff,53,18\"  OK"
        ]
    },
    "gps": [
        {
            "GPRMC": "$GPRMC,000422.800,V,,,,,0.00,0.00,060180,,,N*4E",
            "GPGGA": "$GPGGA,000422.800,,,,,0,0,,,M,,M,,*44"
        },
        {
            "GPRMC": "$GPRMC,000423.800,V,,,,,0.00,0.00,060180,,,N*4F",
            "GPGGA": "$GPGGA,000423.800,,,,,0,0,,,M,,M,,*45"
        },
        {
            "GPRMC": "$GPRMC,000424.800,V,,,,,0.00,0.00,060180,,,N*48",
            "GPGGA": "$GPGGA,000424.800,,,,,0,0,,,M,,M,,*42"
        },
        {
            "GPRMC": "$GPRMC,000425.800,V,,,,,0.00,0.00,060180,,,N*49",
            "GPGGA": "$GPGGA,000425.800,,,,,0,0,,,M,,M,,*43"
        },
        {
            "GPRMC": "$GPRMC,000426.800,V,,,,,0.00,0.00,060180,,,N*4A",
            "GPGGA": "$GPGGA,000426.800,,,,,0,0,,,M,,M,,*40"
        },
        {
            "GPRMC": "$GPRMC,000427.800,V,,,,,0.00,0.00,060180,,,N*4B",
            "GPGGA": "$GPGGA,000427.800,,,,,0,0,,,M,,M,,*41"
        },
        {
            "GPRMC": "$GPRMC,000428.800,V,,,,,0.00,0.00,060180,,,N*44",
            "GPGGA": "$GPGGA,000428.800,,,,,0,0,,,M,,M,,*4E"
        },
        {
            "GPRMC": "$GPRMC,000429.800,V,,,,,0.00,0.00,060180,,,N*45",
            "GPGGA": "$GPGGA,000429.800,,,,,0,0,,,M,,M,,*4F"
        },
        {
            "GPRMC": "$GPRMC,000430.800,V,,,,,0.00,0.00,060180,,,N*4D",
            "GPGGA": "$GPGGA,000430.800,,,,,0,0,,,M,,M,,*47"
        },
        {
            "GPRMC": "$GPRMC,000431.800,V,,,,,0.00,0.00,060180,,,N*4C",
            "GPGGA": "$GPGGA,000431.800,,,,,0,0,,,M,,M,,*46"
        },
        {
            "GPRMC": "$GPRMC,000432.800,V,,,,,0.00,0.00,060180,,,N*4F",
            "GPGGA": "$GPGGA,000432.800,,,,,0,0,,,M,,M,,*45"
        }
    ]
}