{
    "timeStamp": "1511527147",
    "devID": "000000009d38c2c2",
    "totalScanTime": 72,
    "wakeCounter": 1244,
    "ble": {
        "scan1": {
            "00:A0:50:C5:76:DE": "-64",
            "00:A0:50:C5:76:86": "-73",
            "00:A0:50:C5:75:53": "-68",
            "00:A0:50:B2:93:2F": "-93",
            "00:A0:50:C5:75:B4": "-71",
            "00:A0:50:B2:96:EA": "-87",
            "00:A0:50:B2:96:EC": "-89",
            "00:A0:50:B2:94:F1": "-89",
            "00:A0:50:C5:75:74": "-73",
            "18:B3:AC:41:2B:94": "-97",
            "00:A0:50:B3:77:13": "-89",
            "00:A0:50:B2:96:AC": "-86",
            "00:A0:50:C5:65:4D": "-75",
            "08:FC:4F:D9:FB:1F": "-97",
            "00:A0:50:C5:65:17": "-72",
            "00:A0:50:C5:65:4A": "-59",
            "00:A0:50:B2:96:B2": "-71",
            "00:A0:50:C5:65:4C": "-76",
            "00:A0:50:C5:75:6C": "-78",
            "00:A0:50:C5:76:95": "-78",
            "00:A0:50:C5:76:9A": "-74",
            "00:A0:50:C5:76:EA": "-60",
            "00:A0:50:C5:76:94": "-79",
            "00:A0:50:C5:65:11": "-73",
            "00:A0:50:C5:65:1A": "-78",
            "00:A0:50:C5:75:63": "-75",
            "00:A0:50:C5:75:65": "-73",
            "00:A0:50:C5:75:64": "-72",
            "00:A0:50:C5:76:93": "-76",
            "00:A0:50:C5:65:0E": "-64",
            "00:A0:50:C5:76:CB": "-66",
            "00:A0:50:B2:96:DF": "-73",
            "00:A0:50:B2:96:DD": "-86",
            "00:A0:50:B2:93:22": "-91",
            "00:A0:50:B2:93:5F": "-97",
            "00:A0:50:B3:77:09": "-96",
            "00:A0:50:C5:76:8D": "-65",
            "00:A0:50:B2:96:A8": "-89",
            "00:A0:50:B2:96:A4": "-91",
            "00:A0:50:B2:96:A0": "-85",
            "00:A0:50:C5:75:6A": "-71",
            "00:A0:50:B3:77:E1": "-84",
            "00:A0:50:B2:96:61": "-93",
            "00:A0:50:B2:93:24": "-95"
        }
    },
    "dht": [
        " 27,47,1511527153"
    ],
    "gsm": {
        "scan1": [
            "AT+CREG? +CREG: 0,1  OK",
            "AT+CENG=3 OK",
            "AT+COPS=? +COPS: (2,\"IDEA Cellular Limited\",\"IDEA\",\"40422\"),(3,\"BPL USWEST (Maharastra)\",\"BPL MO\",\"40427\"),(3,\"405804\",\"405804\",\"405804\"),(1,\"Maharashtra\",\"CellOne\",\"40466\"),(3,\"AirTel\",\"AirTel\",\"40490\"),,(0-4),(0-2)  OK",
            "AT+CSQ +CSQ: 10,0  OK",
            "AT+CENG? +CENG: 3,0  +CENG: 0,\"404,22,278d,3661,53,19\" +CENG: 1,\"404,22,278d,1507,04,11\" +CENG: 2,\",,0000,ffff,00,17\" +CENG: 3,\",,0000,ffff,00,14\" +CENG: 4,\",,0000,ffff,00,13\" +CENG: 5,\",,0000,ffff,00,11\" +CENG: 6,\",,0000,ffff,00,11\"  OK"
        ]
    },
    "gps": [
        {
            "GPRMC": "$GPRMC,000239.800,V,,,,,0.00,0.00,060180,,,N*42",
            "GPGGA": "$GPGGA,000239.800,,,,,0,0,,,M,,M,,*48"
        },
        {
            "GPRMC": "$GPRMC,000240.800,V,,,,,0.00,0.00,060180,,,N*4C",
            "GPGGA": "$GPGGA,000240.800,,,,,0,0,,,M,,M,,*46"
        },
        {
            "GPRMC": "$GPRMC,000241.800,V,,,,,0.00,0.00,060180,,,N*4D",
            "GPGGA": "$GPGGA,000241.800,,,,,0,0,,,M,,M,,*47"
        },
        {
            "GPRMC": "$GPRMC,000242.800,V,,,,,0.00,0.00,060180,,,N*4E",
            "GPGGA": "$GPGGA,000242.800,,,,,0,0,,,M,,M,,*44"
        },
        {
            "GPRMC": "$GPRMC,000243.800,V,,,,,0.00,0.00,060180,,,N*4F",
            "GPGGA": "$GPGGA,000243.800,,,,,0,0,,,M,,M,,*45"
        },
        {
            "GPRMC": "$GPRMC,000244.800,V,,,,,0.00,0.00,060180,,,N*48",
            "GPGGA": "$GPGGA,000244.800,,,,,0,0,,,M,,M,,*42"
        },
        {
            "GPRMC": "$GPRMC,000245.800,V,,,,,0.00,0.00,060180,,,N*49",
            "GPGGA": "$GPGGA,000245.800,,,,,0,0,,,M,,M,,*43"
        },
        {
            "GPRMC": "$GPRMC,000246.800,V,,,,,0.00,0.00,060180,,,N*4A",
            "GPGGA": "$GPGGA,000246.800,,,,,0,0,,,M,,M,,*40"
        },
        {
            "GPRMC": "$GPRMC,000247.800,V,,,,,0.00,0.00,060180,,,N*4B",
            "GPGGA": "$GPGGA,000247.800,,,,,0,0,,,M,,M,,*41"
        },
        {
            "GPRMC": "$GPRMC,000248.800,V,,,,,0.00,0.00,060180,,,N*44",
            "GPGGA": "$GPGGA,000248.800,,,,,0,0,,,M,,M,,*4E"
        },
        {
            "GPRMC": "$GPRMC,000249.800,V,,,,,0.00,0.00,060180,,,N*45",
            "GPGGA": "$GPGGA,000249.800,,,,,0,0,,,M,,M,,*4F"
        }
    ]
}