{
    "timeStamp": "1510069134",
    "devID": "000000009d38c2c2",
    "totalScanTime": 52,
    "wakeCounter": 1102,
    "ble": {
        "scan1": {
            "00:A0:50:C5:65:25": "-40",
            "00:A0:50:C5:76:8D": "-41",
            "00:A0:50:C5:75:6B": "-45",
            "00:A0:50:C5:65:1B": "-41"
        }
    },
    "dht": [
        " 36,39,1510069140"
    ],
    "gsm": {
        "scan1": [
            "AT+CREG? +CREG: 0,1  OK",
            "AT+CENG=3 OK",
            "AT+COPS=? +COPS: (2,\"IDEA Cellular Limited\",\"IDEA\",\"40422\"),(3,\"405037\",\"405037\",\"405037\"),(3,\"405804\",\"405804\",\"405804\"),(3,\"AirTel\",\"AirTel\",\"40490\"),(3,\"BPL USWEST (Maharastra)\",\"BPL MO\",\"40427\"),(1,\"Maharashtra\",\"CellOne\",\"40466\"),,(0-4),(0-2)  OK",
            "AT+CSQ +CSQ: 29,0  OK",
            "AT+CENG? +CENG: 3,0  +CENG: 0,\"404,22,278d,206d,25,57\" +CENG: 1,\"404,22,278d,2654,02,35\" +CENG: 2,\"404,22,278d,206f,35,32\" +CENG: 3,\"404,22,278d,12cc,49,29\" +CENG: 4,\"404,22,278d,3663,46,28\" +CENG: 5,\"404,22,278d,12cb,02,26\" +CENG: 6,\"404,22,278d,0acb,42,24\"  OK"
        ]
    },
    "gps": [
        {
            "GPRMC": "$GPRMC,100904.000,A,1830.6673,N,07346.3335,E,0.00,123.61,071117,,,A*6A"
        }
    ]
}